{"identifier":"admin","hash":"raRqbvIqY/j/WIkjnyK6Nu+tspl3ZLwYDVxXn7yOZBc=","readPermission":[],"uploadNumber":4611686018427387904,"uploadSize":4611686018427387904,"ownedFiles":[],"GrantToken":true,"readers":[],"Equals":[]}#|#{"identifier":"public","hash":"1yyH0PB3x3ZvKYXfqzDolVw3OhOh6T0xUgOTn1Qv+G4=","readPermission":[],"uploadNumber":0,"uploadSize":0,"ownedFiles":[],"GrantToken":false,"readers":[],"Equals":[]}#|#{"identifier":"","hash":null,"readPermission":null,"uploadNumber":0,"uploadSize":0,"ownedFiles":null,"GrantToken":false,"readers":null,"Equals":null}